circulocov/__init__.py
circulocov/circulocov.py
circulocov/utils/__init__.py
circulocov/utils/average_depth.py
circulocov/utils/counts.py
circulocov/utils/coverage.py
circulocov/utils/create_dataframe.py
circulocov/utils/create_figure.py
circulocov/utils/depth.py
circulocov/utils/extract.py
circulocov/utils/genome_prep.py
circulocov/utils/mapping.py
circulocov/utils/merge_dataframe.py
circulocov/utils/overall_row.py
circulocov/utils/summary.py
circulocov/utils/top_ten.py
circulocov/utils/visualize.py
circulocov-0.1.20240104.dist-info/LICENSE
circulocov-0.1.20240104.dist-info/METADATA
circulocov-0.1.20240104.dist-info/WHEEL
circulocov-0.1.20240104.dist-info/entry_points.txt
circulocov-0.1.20240104.dist-info/top_level.txt
circulocov-0.1.20240104.dist-info/RECORD
