Metadata-Version: 2.1
Name: circulocov
Version: 0.1.20240104
Summary: Circular-Aware Coverage for Draft Genomes
Home-page: https://github.com/erinyoung/CirculoCov
Author: Erin Young
Author-email: eriny@utah.gov
Keywords: bioinformatics,coverage,visualization
Classifier: Programming Language :: Python :: 3
Classifier: Development Status :: 4 - Beta 
Classifier: Intended Audience :: Science/Research
Classifier: Intended Audience :: Developers
Classifier: License :: OSI Approved :: GNU General Public License v3 (GPLv3)
Classifier: Topic :: Scientific/Engineering :: Bio-Informatics 
Requires-Python: >=3.11, <4
License-File: LICENSE
Requires-Dist: pandas
Requires-Dist: pysam
Requires-Dist: matplotlib >=3.0.0
Requires-Dist: numpy
Requires-Dist: pyCirclize
Requires-Dist: biopython
